pyslammer/__init__.py
pyslammer/analytical_sliding_block.py
pyslammer/constants.py
pyslammer/coupled_analysis.py
pyslammer/decoupled_analysis.py
pyslammer/demo_widgets.py
pyslammer/dynamic_response.py
pyslammer/record.py
pyslammer/rigid_analysis.py
pyslammer/sliding_block_analysis.py
pyslammer/utilities.py
pyslammer/sample_ground_motions/Cape_Mendocino_1992_PET-090.csv
pyslammer/sample_ground_motions/Chi-Chi_1999_TCU068-090.csv
pyslammer/sample_ground_motions/Coalinga_1983_PVB-045.csv
pyslammer/sample_ground_motions/Coyote_Lake_1979_G02-050.csv
pyslammer/sample_ground_motions/Duzce_1999_375-090.csv
pyslammer/sample_ground_motions/Imperial_Valley_1979_BCR-230.csv
pyslammer/sample_ground_motions/Kobe_1995_TAK-090.csv
pyslammer/sample_ground_motions/Kocaeli_1999_ATS-090.csv
pyslammer/sample_ground_motions/Landers_1992_LCN-345.csv
pyslammer/sample_ground_motions/Loma_Prieta_1989_HSP-000.csv
pyslammer/sample_ground_motions/Mammoth_Lakes-1_1980_CVK-090.csv
pyslammer/sample_ground_motions/Mammoth_Lakes-2_1980_CVK-090.csv
pyslammer/sample_ground_motions/Morgan_Hill_1984_CYC-285.csv
pyslammer/sample_ground_motions/N_Palm_Springs_1986_WWT-180.csv
pyslammer/sample_ground_motions/Nahanni_1985_NS1-280.csv
pyslammer/sample_ground_motions/Nisqually_2001_UNR-058.csv
pyslammer/sample_ground_motions/Northridge_1994_PAC-175.csv
pyslammer/sample_ground_motions/Northridge_1994_VSP-360.csv
pyslammer-0.2.1.dist-info/METADATA
pyslammer-0.2.1.dist-info/WHEEL
pyslammer-0.2.1.dist-info/licenses/LICENSE.txt
pyslammer-0.2.1.dist-info/RECORD
