Metadata-Version: 2.4
Name: pyslammer
Version: 0.2.1
Summary: Python code for calculating sliding block displacements (based on the USGS software SLAMMER).
Project-URL: Repository, https://github.com/lornearnold/pyslammer
Author: Lorne Arnold, Donald Garcia-Rivas
Maintainer-email: Lorne Arnold <arnoldl@uw.edu>
License:                     GNU GENERAL PUBLIC LICENSE
License-File: LICENSE.txt
Keywords: earthquake,geotech,seismic,sliding block,slope stability
Requires-Python: >=3.11
Requires-Dist: numpy
Requires-Dist: scipy
Requires-Dist: sphinx-book-theme>=1.1.4
Provides-Extra: demo
Requires-Dist: ipywidgets; extra == 'demo'
Requires-Dist: matplotlib; extra == 'demo'
Requires-Dist: pandas; extra == 'demo'
Requires-Dist: sympy; extra == 'demo'
